LinSATNet/__init__.py
LinSATNet/linsat.py
LinSATNet-0.1.3.dist-info/LICENSE
LinSATNet-0.1.3.dist-info/METADATA
LinSATNet-0.1.3.dist-info/WHEEL
LinSATNet-0.1.3.dist-info/top_level.txt
LinSATNet-0.1.3.dist-info/RECORD
